siblink/Command.py
siblink/Config.py
siblink/__init__.py
siblink/cli.py
siblink/commands/__init__.py
siblink/commands/init.py
siblink/commands/pip.py
siblink/commands/run.py
siblink-1.2.2.dist-info/licenses/LICENSE
siblink-1.2.2.dist-info/METADATA
siblink-1.2.2.dist-info/WHEEL
siblink-1.2.2.dist-info/entry_points.txt
siblink-1.2.2.dist-info/top_level.txt
siblink-1.2.2.dist-info/RECORD
